carbonplan_forest_risks/__init__.py
carbonplan_forest_risks/collect.py
carbonplan_forest_risks/prepare.py
carbonplan_forest_risks/utils.py
carbonplan_forest_risks/data/__init__.py
carbonplan_forest_risks/data/catalog.yaml
carbonplan_forest_risks/data/nlcd_albedo_conversions.csv
carbonplan_forest_risks/fit/__init__.py
carbonplan_forest_risks/fit/growth.py
carbonplan_forest_risks/fit/hurdle.py
carbonplan_forest_risks/fit/interp.py
carbonplan_forest_risks/load/__init__.py
carbonplan_forest_risks/load/cmip.py
carbonplan_forest_risks/load/fia.py
carbonplan_forest_risks/load/mask.py
carbonplan_forest_risks/load/mtbs.py
carbonplan_forest_risks/load/nftd.py
carbonplan_forest_risks/load/nlcd.py
carbonplan_forest_risks/load/terraclim.py
carbonplan_forest_risks/load/tiff.py
carbonplan_forest_risks/plot/__init__.py
carbonplan_forest_risks/plot/carto.py
carbonplan_forest_risks/plot/fire.py
carbonplan_forest_risks/plot/line.py
carbonplan_forest_risks/plot/paper.py
carbonplan_forest_risks/plot/xy.py
carbonplan_forest_risks/preprocess/__init__.py
carbonplan_forest_risks/preprocess/fia.py
carbonplan_forest_risks/setup/__init__.py
carbonplan_forest_risks/setup/loading.py
carbonplan_forest_risks/setup/plotting.py
carbonplan_forest_risks-1.0.0.dist-info/LICENSE
carbonplan_forest_risks-1.0.0.dist-info/METADATA
carbonplan_forest_risks-1.0.0.dist-info/WHEEL
carbonplan_forest_risks-1.0.0.dist-info/top_level.txt
carbonplan_forest_risks-1.0.0.dist-info/RECORD
