Metadata-Version: 2.1
Name: carbonplan-forest-risks
Version: 1.0.0
Summary: forest carbon potential and risks
Home-page: https://github.com/carbonplan/forest-risks
Maintainer: Joe Hamman
Maintainer-email: joe@carbonplan.org
License: MIT
Keywords: carbon,data,climate
Platform: UNKNOWN
Requires-Python: >=3.7
Requires-Dist: altair
Requires-Dist: altair-data-server
Requires-Dist: carbonplan
Requires-Dist: carbonplan[styles]
Requires-Dist: dask[complete]
Requires-Dist: fsspec
Requires-Dist: fastparquet
Requires-Dist: google-cloud-storage
Requires-Dist: intake
Requires-Dist: intake-geopandas
Requires-Dist: intake-xarray
Requires-Dist: netcdf4
Requires-Dist: networkx
Requires-Dist: pandas
Requires-Dist: pytest
Requires-Dist: rasterio
Requires-Dist: scikit-learn
Requires-Dist: tenacity
Requires-Dist: urlpath
Requires-Dist: vega-datasets
Requires-Dist: xarray
Requires-Dist: zarr
